us_vis/__init__.py
us_vis/merge.py
us_vis/test.py
us_vis/vis.py
us_vis-1.0.dist-info/METADATA
us_vis-1.0.dist-info/WHEEL
us_vis-1.0.dist-info/top_level.txt
us_vis-1.0.dist-info/RECORD
