Metadata-Version: 2.1
Name: us_vis
Version: 1.0
Summary: Visualisation tools for umbrella sampling calculations
Requires-Dist: pandas
Requires-Dist: matplotlib
Provides-Extra: dev
Requires-Dist: pytest ; extra == 'dev'
Provides-Extra: docs
Requires-Dist: sphinx ; extra == 'docs'
